event_scheduler/__init__.py
event_scheduler/event_scheduler.py
event_scheduler/test_util.py
tests/__init__.py
tests/tests.py
tests/unit_tests/__init__.py
tests/unit_tests/event_scheduler_tests.py
tests/unit_tests/test_util_tests.py
event_scheduler-0.1.3.dist-info/LICENSE
event_scheduler-0.1.3.dist-info/METADATA
event_scheduler-0.1.3.dist-info/WHEEL
event_scheduler-0.1.3.dist-info/top_level.txt
event_scheduler-0.1.3.dist-info/RECORD
