Metadata-Version: 2.1
Name: event-scheduler
Version: 0.1.3
Summary: Always-on event scheduler
Home-page: https://github.com/phluentmed/event-scheduler
Author: Dil Mchaina, Farhan Ahmed
Author-email: phluentmed@gmail.com
License: UNKNOWN
Project-URL: Documentation, https://event-scheduler.readthedocs.io
Project-URL: GitHub, https://github.com/phluentmed/event-scheduler
Keywords: Python Event Scheduler
Platform: UNKNOWN
Classifier: Programming Language :: Python :: 3
Classifier: License :: OSI Approved :: MIT License
Classifier: Operating System :: OS Independent
Requires-Python: >=3.6
License-File: LICENSE
